{
  "department": "Mobile UI Card Generator",
  "date": "2026-07-20",
  "input_sources": [
    "output/reports/daily_niche_ui_candidates.json",
    "output/reports/design_strategy.json"
  ],
  "summary": "Generated a smartphone-first app UI screenshot without sales-copy framing.",
  "scores": {
    "width": 1080,
    "height": 1350,
    "phone_width": 710,
    "phone_height": 1288,
    "png_generated": true
  },
  "risks": [],
  "next_action": "quality gate",
  "candidate_id": "no-selected-candidate",
  "composition": "mobile-app-screen-only",
  "sales_copy_removed": true,
  "phone_ratio": {
    "width": 710,
    "height": 1288
  },
  "card_paths": {
    "html": "output/share-cards/2026-07-20-no-selected-candidate.html",
    "png": "output/share-cards/2026-07-20-no-selected-candidate.png"
  },
  "png_generated": true,
  "png_status": "ok",
  "report": "output/reports/daily_share_card_report.md"
}
