{
  "department": "Scriptwriter Department",
  "date": "2026-07-10",
  "input_sources": [
    "output/reports/daily_niche_ui_candidates.json",
    "output/reports/audience_tone_profile.json",
    "data/post_log.json"
  ],
  "summary": "Generated natural Threads copy from 10 rotating audience-aware structures instead of a single fixed template.",
  "scores": {
    "length": 106,
    "variant_count": 10,
    "max_recent_similarity": 0.122
  },
  "risks": [],
  "next_action": "generate mobile UI share card",
  "post": {
    "date": "2026-07-10",
    "candidate_id": "",
    "text": "あとで見返したい時、小さい不便で時間溶けない？\n\nちゃんと残してるはずなのに、\n残し場所が毎回違う。\n\n・メモ\n・スクショ\n・カレンダー\n・写真フォルダ\n\nスマホUIのアプリがあったら、今のやり方から乗り換える？",
    "alt_text": "候補のスマホアプリ画面",
    "topic_tags": [
      "",
      "ニッチアプリ"
    ],
    "decision": "dry_run",
    "tone_id": "default_light_problem",
    "target_audience": "unclear",
    "variant_id": "02",
    "pattern_id": "time_melts_scene",
    "tone_check_result": {
      "passed": true,
      "tone_id": "default_light_problem",
      "used_words": [
        "メモ"
      ],
      "used_avoid_words": [],
      "line_count": 8,
      "target_audience": "unclear",
      "max_recent_similarity": 0.122
    }
  },
  "tone_variants_path": "output/reports/threads_tone_variants.json"
}
